genetics_viz/__init__.py
genetics_viz/__main__.py
genetics_viz/app.py
genetics_viz/cli.py
genetics_viz/components/__init__.py
genetics_viz/components/column_selector.py
genetics_viz/components/filters.py
genetics_viz/components/header.py
genetics_viz/components/icons.py
genetics_viz/components/tables.py
genetics_viz/components/validation_loader.py
genetics_viz/components/variant_dialog.py
genetics_viz/components/waves_loader.py
genetics_viz/models.py
genetics_viz/pages/__init__.py
genetics_viz/pages/cohort/__init__.py
genetics_viz/pages/cohort/cohort.py
genetics_viz/pages/cohort/components/__init__.py
genetics_viz/pages/cohort/components/dnm_tab.py
genetics_viz/pages/cohort/components/wombat_tab.py
genetics_viz/pages/cohort/family.py
genetics_viz/pages/cohort/home.py
genetics_viz/pages/cohort/variant.py
genetics_viz/pages/validation/__init__.py
genetics_viz/pages/validation/all.py
genetics_viz/pages/validation/file.py
genetics_viz/pages/validation/statistics.py
genetics_viz/pages/validation/wave.py
genetics_viz/pages/validation/waves.py
genetics_viz/pages/validation/waves_backup.py
genetics_viz/utils/__init__.py
genetics_viz/utils/data.py
genetics_viz-0.2.0.dist-info/WHEEL
genetics_viz-0.2.0.dist-info/entry_points.txt
genetics_viz-0.2.0.dist-info/METADATA
genetics_viz-0.2.0.dist-info/RECORD
