Metadata-Version: 2.3
Name: genetics-viz
Version: 0.2.0
Summary: A web-based visualization tool for genetics cohort data
Keywords: genetics,visualization,pedigree,cohort
Author: Freddy Cliquet
Author-email: Freddy Cliquet <fcliquet@pasteur.fr>
Classifier: Development Status :: 3 - Alpha
Classifier: Intended Audience :: Science/Research
Classifier: License :: OSI Approved :: MIT License
Classifier: Programming Language :: Python :: 3
Classifier: Programming Language :: Python :: 3.12
Classifier: Programming Language :: Python :: 3.13
Classifier: Topic :: Scientific/Engineering :: Bio-Informatics
Requires-Dist: nicegui>=2.0.0
Requires-Dist: polars>=1.0.0
Requires-Dist: typer>=0.12.0
Requires-Python: >=3.12
Project-URL: Homepage, https://github.com/bourgeron-lab/genetics-viz
Project-URL: Repository, https://github.com/bourgeron-lab/genetics-viz
Project-URL: Issues, https://github.com/bourgeron-lab/genetics-viz/issues
